README.md
setup.py
bsuite/__init__.py
bsuite/_metadata.py
bsuite/bsuite.py
bsuite/sweep.py
bsuite/sweep_test.py
bsuite.egg-info/PKG-INFO
bsuite.egg-info/SOURCES.txt
bsuite.egg-info/dependency_links.txt
bsuite.egg-info/requires.txt
bsuite.egg-info/top_level.txt
bsuite/baselines/__init__.py
bsuite/baselines/base.py
bsuite/baselines/experiment.py
bsuite/baselines/jax/__init__.py
bsuite/baselines/jax/actor_critic/__init__.py
bsuite/baselines/jax/actor_critic/agent.py
bsuite/baselines/jax/actor_critic/run.py
bsuite/baselines/jax/actor_critic/run_test.py
bsuite/baselines/jax/actor_critic_rnn/__init__.py
bsuite/baselines/jax/actor_critic_rnn/agent.py
bsuite/baselines/jax/actor_critic_rnn/run.py
bsuite/baselines/jax/actor_critic_rnn/run_test.py
bsuite/baselines/jax/boot_dqn/__init__.py
bsuite/baselines/jax/boot_dqn/agent.py
bsuite/baselines/jax/boot_dqn/run.py
bsuite/baselines/jax/boot_dqn/run_test.py
bsuite/baselines/jax/dqn/__init__.py
bsuite/baselines/jax/dqn/agent.py
bsuite/baselines/jax/dqn/run.py
bsuite/baselines/jax/dqn/run_test.py
bsuite/baselines/random/__init__.py
bsuite/baselines/random/agent.py
bsuite/baselines/random/run.py
bsuite/baselines/random/run_test.py
bsuite/baselines/tf/__init__.py
bsuite/baselines/tf/actor_critic/__init__.py
bsuite/baselines/tf/actor_critic/agent.py
bsuite/baselines/tf/actor_critic/run.py
bsuite/baselines/tf/actor_critic/run_test.py
bsuite/baselines/tf/actor_critic_rnn/__init__.py
bsuite/baselines/tf/actor_critic_rnn/agent.py
bsuite/baselines/tf/actor_critic_rnn/run.py
bsuite/baselines/tf/actor_critic_rnn/run_test.py
bsuite/baselines/tf/boot_dqn/__init__.py
bsuite/baselines/tf/boot_dqn/agent.py
bsuite/baselines/tf/boot_dqn/run.py
bsuite/baselines/tf/boot_dqn/run_test.py
bsuite/baselines/tf/dqn/__init__.py
bsuite/baselines/tf/dqn/agent.py
bsuite/baselines/tf/dqn/run.py
bsuite/baselines/tf/dqn/run_test.py
bsuite/baselines/third_party/__init__.py
bsuite/baselines/third_party/dopamine_dqn/__init__.py
bsuite/baselines/third_party/dopamine_dqn/run.py
bsuite/baselines/third_party/openai_dqn/__init__.py
bsuite/baselines/third_party/openai_dqn/run.py
