Metadata-Version: 2.1
Name: bsuite
Version: 0.3.4
Summary: Core RL Behaviour Suite. A collection of reinforcement learning experiments.
Home-page: UNKNOWN
Author: DeepMind
License: Apache License, Version 2.0
Keywords: reinforcement-learning python machine learning
Platform: UNKNOWN
Classifier: Development Status :: 3 - Alpha
Classifier: Environment :: Console
Classifier: Intended Audience :: Science/Research
Classifier: License :: OSI Approved :: Apache Software License
Classifier: Operating System :: POSIX :: Linux
Classifier: Operating System :: Microsoft :: Windows
Classifier: Operating System :: MacOS :: MacOS X
Classifier: Programming Language :: Python :: 3.6
Classifier: Programming Language :: Python :: 3.7
Classifier: Programming Language :: Python :: 3.8
Classifier: Topic :: Scientific/Engineering :: Artificial Intelligence
Provides-Extra: baselines
Provides-Extra: baselines_jax
Provides-Extra: baselines_third_party
Provides-Extra: testing
